setup.cfg
setup.py
src/sms_api/__init__.py
src/sms_api.egg-info/PKG-INFO
src/sms_api.egg-info/SOURCES.txt
src/sms_api.egg-info/dependency_links.txt
src/sms_api.egg-info/requires.txt
src/sms_api.egg-info/top_level.txt