Metadata-Version: 1.1
Name: sms-api
Version: 1.2.0
Summary: SMS API Client, send easy SMS text messages using https://easysms.4simple.org service.
Home-page: https://bitbucket.org/smr-team/easy_sms_python
Author: http://www.4simple.org
Author-email: support@4simple.org
License: UNKNOWN
Keywords: sms,sms easy,sms api
Platform: UNKNOWN
Classifier: Development Status :: 5 - Production/Stable
Classifier: Intended Audience :: Developers
Classifier: License :: OSI Approved :: GNU General Public License v3 (GPLv3)
Classifier: Programming Language :: Python :: 2
Classifier: Programming Language :: Python :: 2.6
Classifier: Programming Language :: Python :: 2.7
Classifier: Programming Language :: Python :: 3
Classifier: Programming Language :: Python :: 3.2
Classifier: Programming Language :: Python :: 3.3
Classifier: Programming Language :: Python :: 3.4
Classifier: Programming Language :: Python :: 3.5
Classifier: Topic :: Software Development
